ltf/__init__.py
ltf/bondingcurves.py
ltf/data/bondingcurves_initial_values.csv
ltf-2021.10.dev2.data/data/data/bondingcurves_initial_values.csv
ltf-2021.10.dev2.dist-info/LICENSE
ltf-2021.10.dev2.dist-info/METADATA
ltf-2021.10.dev2.dist-info/WHEEL
ltf-2021.10.dev2.dist-info/top_level.txt
ltf-2021.10.dev2.dist-info/RECORD
