Metadata-Version: 2.1
Name: ltf
Version: 2021.10.dev2
Summary: Public library of all Token Engineering tools
Home-page: http://github.com/longtailfinancial/ltf_library
Author: Long Tail Financial Corp. Token Engineering Team
Author-email: mohammad@longtailfinancial.com
License: UNKNOWN
Project-URL: Bug Tracker, http://github.com/longtailfinancial/ltf_library/issues
Platform: UNKNOWN
Classifier: Programming Language :: Python :: 3
Classifier: License :: OSI Approved :: MIT License
Classifier: Operating System :: OS Independent
Requires-Python: >=3.7
License-File: LICENSE
Requires-Dist: pandas
Requires-Dist: numpy
Requires-Dist: plotly
